CHANGES.md
HACKING.md
LICENSE
MANIFEST.in
README.md
setup.cfg
setup.py
src/openvario_shell.egg-info/PKG-INFO
src/openvario_shell.egg-info/SOURCES.txt
src/openvario_shell.egg-info/dependency_links.txt
src/openvario_shell.egg-info/entry_points.txt
src/openvario_shell.egg-info/requires.txt
src/openvario_shell.egg-info/top_level.txt
src/ovshell/__init__.py
src/ovshell/api.py
src/ovshell/app.py
src/ovshell/device.py
src/ovshell/main.py
src/ovshell/ovos.py
src/ovshell/process.py
src/ovshell/py.typed
src/ovshell/screen.py
src/ovshell/settings.py
src/ovshell/testing.py
src/ovshell/widget.py
src/ovshell/ui/__init__.py
src/ovshell/ui/apps.py
src/ovshell/ui/mainmenu.py
src/ovshell/ui/settings.py
src/ovshell_connman/__init__.py
src/ovshell_connman/agent.py
src/ovshell_connman/agentiface.py
src/ovshell_connman/api.py
src/ovshell_connman/app.py
src/ovshell_connman/dbusiface.py
src/ovshell_connman/ext.py
src/ovshell_connman/indicator.py
src/ovshell_connman/manager.py
src/ovshell_connman/model.py
src/ovshell_core/__init__.py
src/ovshell_core/aboutapp.py
src/ovshell_core/devindicators.py
src/ovshell_core/devsim.py
src/ovshell_core/ext.py
src/ovshell_core/gpstime.py
src/ovshell_core/opkg.py
src/ovshell_core/rotation.py
src/ovshell_core/serial.py
src/ovshell_core/settings.py
src/ovshell_core/setupapp.py
src/ovshell_core/sysinfo.py
src/ovshell_core/upgradeapp.py
src/ovshell_fileman/__init__.py
src/ovshell_fileman/api.py
src/ovshell_fileman/backupapp.py
src/ovshell_fileman/downloadapp.py
src/ovshell_fileman/downloader.py
src/ovshell_fileman/ext.py
src/ovshell_fileman/mountwatch.py
src/ovshell_fileman/rsync.py
src/ovshell_fileman/usbcurtain.py
src/ovshell_fileman/utils.py
src/ovshell_xcsoar/__init__.py
src/ovshell_xcsoar/ext.py
tests/__init__.py
tests/conftest.py
tests/fixtures/__init__.py
tests/fixtures/urwid.py
tests/ovshell_connman_tests/__init__.py
tests/ovshell_connman_tests/stubs.py
tests/ovshell_connman_tests/test_agent.py
tests/ovshell_connman_tests/test_agentiface.py
tests/ovshell_connman_tests/test_app.py
tests/ovshell_connman_tests/test_indicator.py
tests/ovshell_connman_tests/test_manager.py
tests/ovshell_core_tests/__init__.py
tests/ovshell_core_tests/test_aboutapp.py
tests/ovshell_core_tests/test_core_ext.py
