Metadata-Version: 2.1
Name: openvario-shell
Version: 0.7.8
Summary: Main Menu Shell for OpenVario
Home-page: https://github.com/kedder/openvario-shell
Author: Andrey Lebedev
Author-email: andrey.lebedev@gmail.com
Keywords: openvario tui menu shell
Classifier: Development Status :: 3 - Alpha
Classifier: Intended Audience :: End Users/Desktop
Classifier: License :: OSI Approved :: GNU Lesser General Public License v3 (LGPLv3)
Classifier: Programming Language :: Python :: 3
Classifier: Programming Language :: Python :: 3.9
Classifier: Programming Language :: Python :: 3.10
Requires-Python: <4,>=3.7
Provides-Extra: dev
Provides-Extra: test
License-File: LICENSE
